cmcl/ORIG__init__.py
cmcl/__init__.py
cmcl/io.py
cmcl-0.1.2.dist-info/DESCRIPTION.rst
cmcl-0.1.2.dist-info/METADATA
cmcl-0.1.2.dist-info/RECORD
cmcl-0.1.2.dist-info/WHEEL
cmcl-0.1.2.dist-info/metadata.json
cmcl-0.1.2.dist-info/top_level.txt
